Workbook

Sheet Lab1
A1: 115.109: Topic 1 Lab Worksheet
A2: Due date: August 3 | D2: Version: 1 (09.07)
A4: Task 1:
A5: This bike is a "classic seller" for the "classic rider". It last sold for RRP $439.99
E19: Answer | G19: Show Formula Used
A20: 1.1 | B20: What is the ex-GST price? | E20: =439.99/1.15 -> 382.6 | G20: =(439.99/1.15)
A21: 1.2 | B21: What is the GST included in the RRP? | E21: =((439.99 * 0.15) / 1.15) -> 57.39 | G21: =((439.99 * 0.15) / 1.15)
A23: If it costs $200 (ex-GST) to add the bike to inventory: | D23: COGS: | E23: 200
A24: 1.3 | B24: What is the Gross Margin $? (GM) | E24: =(E20 - E23) -> 182.6 | G24: =(E20 - E23)
A25: 1.4 | B25: What is the GM%? | E25: =((E24 / E20) * 100) -> 47.726085 | G25: =((E24 / E20) * 100)
A27: Recalculate 1.3-1.4 if the next purchase order raises the per unit acquisition cost (COGS) to $300 [formulas no longer required]
A28: 1.5 | B28: What is the COGS for the latest order? | E28: 300
A29: 1.6 | B29: What is the Gross Margin $? | E29: =(E20 - E28) -> 82.6
A30: 1.7 | B30: What is the Gross Margin %? | E30: =((E29 / E20) * 100) -> 21.589127
A31: 1.8 | B31: What is the markup %? | E31: =(E29/E28) * 100 -> 27.533333
A33: Task 2:
A34: A second model is added, a fully-suspended mountain e-bike.
A35: It has an RRP of $6999.99, but has a 20% 'launch' discount.
A47: Complete cells E52 to E61 based on the RRP, and G51:G61 based on the 20% discount.
A48: After weak sales, Torpedo7 then decide to further reduce the price to clear ("burn") the item, and price the bike at $5099.99 (including GST)
A49: Complete cells H52:H61 based on clearance ('burn') price.
E50: Full price: | G50: With 20% discount | H50: Clearance price:
D51: RRP: | E51: 6999.99 | G51: =(E51 * 0.8) -> 5599.992 | H51: 5099.99
A52: 2.1 | B52: What is the ex-GST price? | E52: =(E51/1.15) -> 6086.9478 | G52: =(E52 * 0.8) -> 4869.5583 | H52: =(H51 / 1.15) -> 4434.7739
B53: % discount for clearance | H53: =(H51-E51)/E51*100 -> -27.142896
A54: If it costs $4600 to add the bike to inventory: | D54: COGS | E54: 4600 | G54: 4600 | H54: 4600
A55: 2.2 | B55: What is the Gross Margin $? | E55: =( E52 - E54) -> 1486.9478 | G55: =( G52 - G54) -> 269.55826 | H55: =( H52 - H54) -> -165.22609
A56: 2.3 | B56: What is the GM%? | E56: =(E55 / E52) * 100 -> 24.428463 | G56: =(G55 / G52) * 100 -> 5.5355793 | H56: =( H55 / H52 ) * 100 -> -3.7256936
A58: Units sold at that RRP: | E58: 10 | G58: 20 | H58: 30
A59: 2.4 | B59: What is the total sales revenue? (ex-GST) | E59: =(E52 * E58) -> 60869.478 | G59: =(G52 *G58) -> 97391.165 | H59: =(H52 * H58) -> 133043.22
A60: 2.5 | B60: What is the total gross margin $? | E60: =(E55*E58) -> 14869.478 | G60: =(G55 * G58) -> 5391.1652 | H60: =(H55 * H58) -> -4956.7826
A61: 2.6 | C61: and %? | E61: =(E55 / E52 ) * 100 -> 24.428463 | G61: =(G55 / G52 ) * 100 -> 5.5355793 | H61: =(H55 / H52 ) * 100 -> -3.7256936
A62: 2.7 | B62: Was the discount worthwhile in profit terms?
A66: Task 3: Using the "SustainabilityData-10%sample" datasheet, do some data checks
A67: This is an ~10% subsample: a selection from a larger dataset, which we will use in future labs (and in the report).
A68: For now, we need to check all data is OK (no missing data), and transform column B
A69: Process:
A70: 1) Do the following in the SustainabilityData-10%sample tab at the bottom of the spreadsheet
A71: 2) Use the quick scrolling keys to go the bottom and right of the dataset: holding the Cntrl key (Windows) or Command key (Mac) and press the down arrow key to go the bottom of an 'array' (contiguous set of data)
A72: Hold the Cntrl / Command key (Windows/Mac) and press the right arrow key to go the far right of an 'array' (contiguous set of data).
A73: NB: if there are any breaks in the data, the highlighted cell (the one shown at the top of the spreadsheet) will stop just before the break.
A74: 3) We need to remove the 'sec' (for seconds) that is in column 2. We could [BUT WE WON'T] select the column and use Home menu > Find > Replace (Find=" sec", Replace =""), or we could Parse the data.
A75: Parsing means splitting data. We want to Parse the data in cells B5:B108 (in the SustainabilityData sheet) so that the number remains in column B, and the " sec" goes into column C (and could then be deleted).
A76: 4) Select the data from cells B5:B108, by clicking in cell B5, then hold the Shift+Control/Command and the down arrow key. (Holding Shift selects as you scroll.)
A77: 5) With the selected data, choose the 'Text to Columns' button on the Data toolbar (or for Macs, also in the Data menu)
... A93: NB: if you only selected column D, Excel would prompt you to Extend the range - but best to select all the data first.
A94: 9) Interpret the result: any unusually long or short completion times [in min]? | G94: What is the longest completion time? | I94: 244.5 | J94: minutes
A96: Task 4: Use XLOOKUP to find the respondent with the shortest time
A97: XLOOKUP is a powerful tool for extracting data from arrays(columns or rows of data). It combines the previous HLOOKUP (for rows) and VLOOKUP (for columns) into one, and can return multiple results (ie, an array).
A98: 1) Which response had the shortest response time? You could look at the sorted data and figure out which row and therefore lookup the response ID, or use the XLOOKUP formula.
A99: 2) The function uses a 'lookup_value' {in our case, the shortest time}, a 'lookup_array' {the data it compares that value to: cells D5:D108}, and a 'return_array' {the value we want: the corresponding response ID in cells A5:A108}
A100: 3) First find the shortest time, and enter this into cell C117 of the SustainabilityData-10%sample sheet. You can enter the value itself from the sorted data, or use the formula =min(D5:D108)
A101: 4) Then in cell D117 type the following formula: =XLOOKUP(C117,D5:D108,A5:A108) and copy the result here: | I101: 81 | J101: (Enter response number only in Red Box Quiz: drop the leading P}
A102: {NB: The lookup_value could be a fixed value, rather than the cell reference shown above, but in general it is best to avoid fixed values in formulas.}
A104: Task 5: Using the "SustainabilityData-10%sample" datasheet, get frequencies of some demographic data using COUNTIF
A105: 1) Determine the gender composition of the survey respondents. In cell E4, we can see there are three options: 1=Male, 2=Female and 3=Gender diverse (eg transgender, intersex)
A106: To determine how many males we have, we could sort the whole dataset by column E, and then work out how many 1s there are. Or we can use a function: CountIf
A107: 2) In cell E110 of the SustainabilityData-10%sample sheet, enter the formula =COUNTIF(E5:E108,1), which counts how many cells in the range above contain a "1".
A108: 3) Copy the formula in E110 of the SustainabilityData sheet, and paste in E111 of that sheet. Note what happens: because you have gone down a row, Excel changes the range accordingly [=COUNTIF(E6:G108,1)]
A109: 4) To correct this, in E110 add $ before the row numbers =COUNTIF(E$5:E$108,1) and copy and paste again to E111, and E112
A110: The $ anchors a cell reference: in front of a letter, it fixes the column; in front of a number, it fixes the row. (You can fix both at the same time if you wish: $E$5)
A111: 5) Now change the ,1) in the E111 formula to ,2); and in E112 to ,3), to find how many 2s and 3s there are.
A112: 6) Copy and paste the results in the table below - but because this table is formatted differently, with rows and columns swapped around, you need to Paste Special (Transpose).
A113: [Alternatively, you can simply refer from this sheet to that sheet: I have entered this for you in cell B110 of this sheet - and you can ignore the instructions in the next two lines - just copy Cell B110 and paste into C110 and D110, and update to the appropriate cells in the SustainabilityData sheet.]
A114: Copy cells E110:E112 from the SustainabilityData-10%sample sheet, and in cell B110 below in this sheet, right-click and choose Paste Special > and locate the Paste Special entry (not any of the pre-formatted options)
A115: In the Paste Special box, select Values and Transpose. | E115: Complete the table:
B116: Males =1 | C116: Females =2 | D116: Diverse =3 | E116: Total
A117: Frequencies | B117: 28 | C117: 76 | D117: 0 | E117: =B117+C117+D117 -> 104
A118: % of respondents | B118: =B117/$E117*100 -> 26.923077 | C118: =C117/$E117*100 -> 73.076923 | D118: =D117/$E117*100 -> 0 | E118: =SUM(B118:D118) -> 100
A120: 7) Now do the same for columns H, I and J of the SustainabilityData-10%sample sheet. These are 'dummy' variables, where the answer options are either selected or not. In column H this is a 2 (if seelcted) or blank; in column I a 3 or blank; in column J a 4 or blank.
A121: For now, calculate how many respondents selected these options in cells H5:H108, I5:I108 and J5:J108, into cells H114:J114 in the SustainabilityData sheet. Copy and Paste Special > Values and Transpose those answers below.
A122: To calculate the non-selected, you can use the total sample size (104) minus the number selected
A124: Question: | B124: Selected | C124: Not selected | E124: Answer coding
A125: Enviro responsible | B125: 74 | C125: =104-B125 -> 30 | E125: 2 if selected, otherwise blank
A126: Zero waste | B126: 41 | C126: =104-B126 -> 63 | E126: 3 if selected, otherwise blank
A127: Social responsible | B127: 54 | C127: =104 - B127 -> 50 | E127: 4 if selected, otherwise blank
A130: <<End of Lab 1>>
A132: AI Declaration for Lab 1:
A133: TRUE | B133: I have not used any AI tools or technologies to prepare this assessment
A134: (tick one) | B134: OR
A135: FALSE | B135: I acknowledge the use of [AI tool or technology name and link] to generate [summary of what was generated]:

Sheet Lab2
A1: 115.109: Topic 2 Lab Worksheet | E1: Your Name: | F1: Savnit Prasad
A2: ='Lab1'!A2 -> Due date: August 3 | C2: ='Lab1'!D2 -> Version: 1 (09.07) | E2: Student ID: | F2: 26019118
A4: Task 1:
A5: Locate the The Warehouse Group 2024 and 2025 Income Statements: extracts available in Week 1 lecture notes
A6: Links to financial statements:
A7: 2025 Annual Report financial statement: | B7: https://www.thewarehousegroup.co.nz/download_file/force/83c5e7a5-091c-45a0-8371-f47056936994/174 | G7: p. 36
A8: 2024 Annual Report financial statement: | B8: https://www.thewarehousegroup.co.nz/download_file/force/5a624589-60db-46c4-ae0a-c630e68b01eb/174 | G8: p. 44 | H8: (includes 2023 info: both 52 week periods)
A10: Complete the following table:
A11: Financial Year ending July | B11: (Income statements reported in $000s - paste into the formula bar not the actual cell, to retain formatting.)
B12: 2025 | C12: 2024 | E12: Var | F12: % var | G12: 2023 | I12: Var | J12: % var
C13: (restated in 2024: use the values from 2024 report)
A14: Sales (Total Revenue) | B14: 3086725 | C14: 3037597 | D14: =F14 -> 0.016173311 | E14: =B14-C14 -> 49128 | F14: =E14/C14 -> 0.016173311 | G14: 3236912 | H14: =J14 -> -0.061575662 | I14: =C14-G14 -> -199315 | J14: =I14/G14 -> -0.061575662
A15: COGS (Cost of Retail Goods Sold) | B15: 2091643 | C15: 2016731 | D15: =F15 -> -0.037145261 | E15: =-(B15-C15) -> -74912 | F15: =-(B15-C15)/C15 -> -0.037145261 | G15: 2148681 | H15: =J15 -> 0.061409767 | I15: =-(C15-G15) -> 131950 | J15: =I15/G15 -> 0.061409767
A16: COGS % sales revenue | B16: =B15/B14 -> 0.67762531 | C16: =C15/C14 -> 0.66392316 | D16: =F16 -> -0.013702155 | E16: =-(B16-C16) -> -0.013702155 | F16: =-(B16-C16) -> -0.013702155 | G16: =G15/G14 -> 0.66380581 | H16: =J16 -> -0.00011734786 | I16: =-(C16-G16) -> -0.00011734786 | J16: =I16 -> -0.00011734786
A17: Gross Profit $ | B17: =B14-B15 -> 995082 | C17: =C14-C15 -> 1020866 | D17: =F17 -> -0.025256988 | E17: =B17-C17 -> -25784 | F17: =(B17-C17)/C17 -> -0.025256988 | G17: =G14-G15 -> 1088231 | H17: =J17 -> -0.061903217 | I17: =C17-G17 -> -67365 | J17: =I17/G17 -> -0.061903217
A18: GP % sales revenue | B18: =B17/B14 -> 0.32237469 | C18: =C17/C14 -> 0.33607684 | D18: =F18 -> -0.013702155 | E18: =B18-C18 -> -0.013702155 | F18: =B18-C18 -> -0.013702155 | G18: =G17/G14 -> 0.33619419 | H18: =J18 -> -0.00011734786 | I18: =C18-G18 -> -0.00011734786 | J18: =I18 -> -0.00011734786
A19: CODB (Lease, Employee, Depreciation,Other expense) | B19: =526520 + 156524 + 285836 -> 968880 | C19: =512146 + 158558 +290284 -> 960988 | D19: =F19 -> -0.0082123814 | E19: =-(B19-C19) -> -7892 | F19: =-(B19-C19)/C19 -> -0.0082123814 | G19: =535770 + 151891 + 286615 -> 974276 | H19: =J19 -> 0.013638846 | I19: =-(C19-G19) -> 13288 | J19: =I19/G19 -> 0.013638846
A20: CODB % sales revenue | B20: =B19/B14 -> 0.31388608 | C20: =C19/C14 -> 0.31636455 | D20: =F20 -> 0.0024784707 | E20: =-(B20-C20) -> 0.0024784707 | F20: =-(B20-C20) -> 0.0024784707 | G20: =G19/G14 -> 0.30098934 | H20: =J20 -> -0.015375209 | I20: =-(C20-G20) -> -0.015375209 | J20: =I20 -> -0.015375209
A21: EBIT (Earnings before Interest and Tax) from retail operations | B21: =B17-B19 -> 26202 | C21: =C17-C19 -> 59878 | D21: =F21 -> -0.56241023 | E21: =B21-C21 -> -33676 | F21: =(B21-C21)/C21 -> -0.56241023 | G21: =G17-G19 -> 113955 | H21: =J21 -> -0.47454697 | I21: =C21-G21 -> -54077 | J21: =I21/G21 -> -0.47454697
A22: EBIT % sales revenue | B22: =B21/B14 -> 0.0084886085 | C22: =C21/C14 -> 0.019712292 | D22: =F22 -> -0.011223684 | E22: =B22-C22 -> -0.011223684 | F22: =B22-C22 -> -0.011223684 | G22: =G21/G14 -> 0.03520485 | H22: =J22 -> -0.015492557 | I22: =C22-G22 -> -0.015492557 | J22: =I22 -> -0.015492557
A24: Interpret the table: what improved, and did not, between 2023-2024, and 2024-2025? | E24: {you can resize this box if you want}
A29: Task 2: Analyse sustainability knowledge (SustainabilityData-10%sample)
A30: 1) The CountIf function used in Lab1 used a fixed criterion to determine what to count in a specified range of data (eg 2 or 3). The criterion can also refer to a cell, and so can vary.
A31: Use the following table to determine the frequencies of each response level for the two 'Subjective Knowledge' questions (columns AI, AJ and AK in the SustainabilityData sheet)
A32: 2) In cell C38 of this sheet, enter the formula: =COUNTIF('SustainabilityData-10%sample'!AI$5:AI$108,$B38) [you can copy this, and paste into the formula bar for that cell]
A33: (We use a $ in front of the numbers so the specified range stays the same when you copy formula down the next six rows;
A34: AND in front of the letter B so that the criterion stays the same when you copy across to columns D and E)
A35: 3) Now copy cell C38, and Paste Special > Formulas into C38:E42 (select the whole range when Pasting Special) [dragging will overwrite the green and red box formatting, so don't do that!]
B37: Response level | C37: Column AI: "I have a good knowledge about sustainability issues" | D37: Column AJ: "I know a great deal about sustainability and sustainability matters" | E37: Column AK: "I know a lot about sustainable products and brands sold in the marketplace" | F37: % of respondents in column AI | G37: % of respondents in column AJ | H37: % of respondents in column AK
B38: 1 | C38: =COUNTIF('SustainabilityData-10%sample'!AI$5:AI$108,$B38) -> 5 | D38: =COUNTIF('SustainabilityData-10%sample'!AJ$5:AJ$108,$B38) -> 7 | E38: =COUNTIF('SustainabilityData-10%sample'!AK$5:AK$108,$B38) -> 11 | F38: =C38/C$43*100 -> 4.8076923 | G38: =D38/D$43*100 -> 6.7307692 | H38: =E38/E$43*100 -> 10.576923
B39: 2 | C39: =COUNTIF('SustainabilityData-10%sample'!AI$5:AI$108,$B39) -> 22 | D39: =COUNTIF('SustainabilityData-10%sample'!AJ$5:AJ$108,$B39) -> 24 | E39: =COUNTIF('SustainabilityData-10%sample'!AK$5:AK$108,$B39) -> 27 | F39: =C39/C$43*100 -> 21.153846 | G39: =D39/D$43*100 -> 23.076923 | H39: =E39/E$43*100 -> 25.961538
B40: 3 | C40: =COUNTIF('SustainabilityData-10%sample'!AI$5:AI$108,$B40) -> 32 | D40: =COUNTIF('SustainabilityData-10%sample'!AJ$5:AJ$108,$B40) -> 33 | E40: =COUNTIF('SustainabilityData-10%sample'!AK$5:AK$108,$B40) -> 30 | F40: =C40/C$43*100 -> 30.769231 | G40: =D40/D$43*100 -> 31.730769 | H40: =E40/E$43*100 -> 28.846154
B41: 4 | C41: =COUNTIF('SustainabilityData-10%sample'!AI$5:AI$108,$B41) -> 36 | D41: =COUNTIF('SustainabilityData-10%sample'!AJ$5:AJ$108,$B41) -> 32 | E41: =COUNTIF('SustainabilityData-10%sample'!AK$5:AK$108,$B41) -> 31 | F41: =C41/C$43*100 -> 34.615385 | G41: =D41/D$43*100 -> 30.769231 | H41: =E41/E$43*100 -> 29.807692
B42: 5 | C42: =COUNTIF('SustainabilityData-10%sample'!AI$5:AI$108,$B42) -> 9 | D42: =COUNTIF('SustainabilityData-10%sample'!AJ$5:AJ$108,$B42) -> 8 | E42: =COUNTIF('SustainabilityData-10%sample'!AK$5:AK$108,$B42) -> 5 | F42: =C42/C$43*100 -> 8.6538462 | G42: =D42/D$43*100 -> 7.6923077 | H42: =E42/E$43*100 -> 4.8076923
B43: Total | C43: =SUM(C38:C42) -> 104 | D43: =SUM(D38:D42) -> 104 | E43: =SUM(E38:E42) -> 104
A45: Task 3: Contrast subjective knowledge of sustainability
A46: 1) Calculate the % of total respondents in cells C38:C42 above. For cell F38, enter the formula =C38/C$43*100
A47: 2) What would happen if you copy that formula into cell E39 WITHOUT that dollar sign? (see hint in row 33 above)
A48: 3) Do the equivalent calculations for G38:H42
A49: 4) How knowledgeable do respondents claim to be?
A57: Task 4: Create a bar chart of the three % columns in Task 2 above
A58: 1) Select cells F37:H42 above, and Insert ribbon > insert Column > 2D Column.
A59: 2) Click on the first bar (mine is blue), and inspect the formula bar.
A60: This shows the information Excel uses to construct the chart
A61: The first information (Lab2!$F$37) determines what goes into the legend.
A62: The second bit is the X-axis info, and is currently missing (nothing shows between the commas)
A63: The third bit is the data range; and the fourth is the series order
... A100: Chart: Pie ↓
G101: Answer: The pie chart looks the same, except the values will be shown differently based on what the user has chosen (percentage or number).
A117: Bonus Task 6: Create a Line Chart of the quarterly price of petrol from 1974 to 2026, in nominal and real prices
A118: The Ministry of Business, Innovation and Employment publishes qarterly fuel prices, in cents per Litre:
A119: https://www.mbie.govt.nz/building-and-energy/energy-and-natural-resources/energy-statistics-and-modelling/energy-statistics/energy-prices
A120: With such a long time series (something we will return to in Topic 11), there has been a lot of inflation along the way, so we can't just look at (nominal) prices at the time (eg 12.3 c/L in March 1974 vs 269.8 in March 2026)
A121: The Reserve Bank publishes the Consumer Price Index going back to 1920, and we can 'inflate' historical prices to their current 'real' equivalent values.
A122: https://www.rbnz.govt.nz/statistics/series/economic-indicators/prices
A123: 6.1: In the following data series, complete the CPI inflator series (E131:BB131), by continuing the pattern on from B131:D131. {How: select B131:D131, then drag the bottom-right corner drag handle across to BB131}
A124: 6.2: Then complete the Real (inflated) petrol price (E129:BB129), and construct a Line chart of the real (inflated) and nominal petrol prices from 1974 to 2026
A126: March Year: | B126: 27089 | C126: 27454 | D126: 27820 | E126: 28185 | F126: 28550 | G126: 28915 | H126: 29281 | I126: 29646 | J126: 30011 | K126: 30376 | L126: 30742 | M126: 31107 | N126: 31472 | O126: 31837 | P126: 32203 | Q126: 32568 | R126: 32933 | S126: 33298 | T126: 33664 | U126: 34029 | V126: 34394 | W126: 34759 | X126: 35125 | Y126: 35490 | Z126: 35855 | AA126: 36220 | AB126: 36586 | AC126: 36951 | AD126: 37316 | AE126: 37681 | AF126: 38047 | AG126: 38412 | AH126: 38777 | AI126: 39142 | AJ126: 39508 | AK126: 39873 | AL126: 40238 | AM126: 40603 | AN126: 40969 | AO126: 41334 | AP126: 41699 | AQ126: 42064 | AR126: 42430 | AS126: 42795 | AT126: 43160 | AU126: 43525 | AV126: 43891 | AW126: 44256 | AX126: 44621 | AY126: 44986 | AZ126: 45352 | BA126: 45717 | BB126: 46082
A127: Petrol (c/l) regular (nominal) | B127: 12.3 | C127: 16.4 | D127: 26.1 | E127: 26.1 | F127: 28.7 | G127: 30.7 | H127: 46.5 | I127: 56 | J127: 60 | K127: 68 | L127: 68 | M127: 87 | N127: 86.333333 | O127: 85 | P127: 89 | Q127: 85.9 | R127: 90.1 | S127: 97.7 | T127: 94.8 | U127: 98.7 | V127: 88.3 | W127: 90.9 | X127: 90.1 | Y127: 90.9 | Z127: 89 | AA127: 80.9 | AB127: 97.1 | AC127: 104.4 | AD127: 97 | AE127: 110.2 | AF127: 109.8 | AG127: 118.3 | AH127: 146.1 | AI127: 142.3 | AJ127: 171.6 | AK127: 155.5 | AL127: 173.2 | AM127: 203 | AN127: 210.3 | AO127: 210.5 | AP127: 211.2 | AQ127: 178.8 | AR127: 169 | AS127: 189.8 | AT127: 200 | AU127: 201.2 | AV127: 208.9 | AW127: 200.3 | AX127: 266.8 | AY127: 245.1 | AZ127: 274.5 | BA127: 266.7 | BB127: 269.8
A128: Petrol (c/l) (real: MBIE) | B128: 183.66324 | C128: 216.30496 | D128: 293.80208 | E128: 258.49447 | F128: 247.96882 | G128: 240.27874 | H128: 307.42428 | I128: 321.26133 | J128: 297.21862 | K128: 299.03066 | L128: 289.00176 | M128: 326.04249 | N128: 286.42429 | O128: 238.38858 | P128: 229.04394 | Q128: 212.52648 | R128: 208.29007 | S128: 216.07424 | T128: 208.00536 | U128: 214.49287 | V128: 189.42321 | W128: 187.50076 | X128: 181.82936 | Y128: 180.22254 | Z128: 174.20152 | AA128: 158.49183 | AB128: 187.44577 | AC128: 195.55362 | AD128: 177.11206 | AE128: 196.26602 | AF128: 192.57209 | AG128: 201.86731 | AH128: 241.30392 | AI128: 229.21599 | AJ128: 267.41033 | AK128: 235.33327 | AL128: 256.86365 | AM128: 288.18596 | AN128: 293.93255 | AO128: 291.70602 | AP128: 288.25646 | AQ128: 243.42266 | AR128: 229.12203 | AS128: 251.8646 | AT128: 262.51236 | AU128: 260.22651 | AV128: 263.50789 | AW128: 248.87463 | AX128: 310.02067 | AY128: 267.03424 | AZ128: 287.49921 | BA128: 272.44873 | BB128: 267.38208
A129: Petrol (c/l) (real: inflated) | B129: =B127*B131 -> 185.05281 | C129: =C127*C131 -> 217.42178 | D129: =D127*D131 -> 296.16864 | E129: =E127*E131 -> 260.80522 | F129: =F127*F131 -> 249.54091 | G129: =G127*G131 -> 241.80765 | H129: =H127*H131 -> 309.76866 | I129: =I127*I131 -> 324.60606 | ... BB129: =BB127*BB131 -> 269.8
A130: CPI Index | B130: 89 | C130: 101 | D130: 118 | E130: 134 | F130: 154 | G130: 170 | H130: 201 | I130: 231 | J130: 268 | K130: 302 | L130: 312 | M130: 354 | N130: 400 | O130: 473 | P130: 516 | Q130: 536 | R130: 574 | S130: 600 | T130: 605 | U130: 611 | V130: 619 | W130: 643 | X130: 658 | Y130: 669 | Z130: 678 | AA130: 677 | AB130: 687 | AC130: 708 | AD130: 727 | AE130: 745 | AF130: 757 | AG130: 778 | AH130: 803 | AI130: 824 | AJ130: 852 | AK130: 877 | AL130: 895 | AM130: 935 | AN130: 949 | AO130: 958 | AP130: 972 | AQ130: 975 | AR130: 979 | AS130: 1000 | AT130: 1011 | AU130: 1026 | AV130: 1052 | AW130: 1068 | AX130: 1142 | AY130: 1218 | AZ130: 1267 | BA130: 1299 | BB130: 1339
A131: CPI Inflator | B131: =$BB130/B130 -> 15.044944 | C131: =$BB130/C130 -> 13.257426 | D131: =$BB130/D130 -> 11.347458 | E131: =$BB130/E130 -> 9.9925373 | F131: =$BB130/F130 -> 8.6948052 | G131: =$BB130/G130 -> 7.8764706 | H131: =$BB130/H130 -> 6.6616915 | I131: =$BB130/I130 -> 5.7965368 | ... BB131: =$BB130/BB130 -> 1
A133: 6.3: Insert Line Chart here for bonus marks: include all three data series in rows 127 and 129
A134: {NB: your chart might be created over in columns AR onwards: cut it there, and paste it here, then resize to the space available} | H134: How? Create a chart with all three data series, then select the real: MBIE series (should be series 2) and delete/remove it (click the minus under Chart Design > Select Data, or click on the chart series you want to remove and press the Delete key
A135: NB: the lines should converge over time, and be the same at March 2026. I show a version of this chart in the Topic 2 lecture | H135: Then edit the X axis so that it shows either just the year, or month-year FOR MARCH (it will likely default to January, which is wrong)
A154: <<End of Lab 2>>
A155: AI Declaration for Lab 2:
A156: TRUE | B156: I have not used any AI tools or technologies to prepare this assessment
A157: (tick one) | B157: OR
A158: FALSE | B158: I acknowledge the use of [AI tool or technology name and link] to generate [summary of what was generated]:

Sheet SustainabilityData-10%sample
A1: Variable Group | G1: What does sustainability mean to you? (select all that apply) | V1: Sustainable intentions and behaiour | AC1: Sustainability literacy
A2: Variable | B2: Survey Duration (text) | D2: Duration (min) | E2: Gender | F2: Age | G2: Corporate citizenship | H2: Enviro responsible | I2: Zero waste | J2: Social responsible | K2: Carbon emissions | L2: Renewables | M2: Ecosystems | N2: Climate change | O2: Social well-being | P2: Traceability | Q2: Water | R2: Waterways | S2: Limiting growth | T2: Not sure | U2: Number of Items picked | V2: HowOftenBuy | W2: LikelyPayMore | X2: WillingPayMore | Y2: AcceptablePayMore | Z2: Return Packaging | AA2: Bottle Deposit scheme | AB2: Household Income | AC2: Capable to solve | AD2: Contribute | AE2: Can help | AF2: Purchase effect | AG2: Positive effect | AH2: Individual difference | AI2: Good knowledge | AJ2: Know sustainability | AK2: Know sustainable brands
A3: Question | B3: Elapsed time to complete survey | D3: Calculation based on elapsed time | E3: Which gender do you identify with? | F3: Which of the following age groups do you fit into:Â | G3: Good corporate citizenship | H3: Being environmentally responsible | I3: Targeting zero waste | J3: Being socially responsible | K3: Carbon emission reduction | L3: Using renewable resources | M3: Protecting ecosystems | N3: Having actionable plans for climate change | O3: Having social well-being focus rather than economic progress | P3: Traceability (can trace where the product has come from "farm to fork") | Q3: Conserving water | R3: Cleaning our waterways and oceans | S3: Limiting population and economic growth | U3: Items Picked | V3: How often do you buy a product that has come from a business that implements sustainable practices? | W3: How likely are you to pay more for a product that has come from a business that implements sustainable practices? | X3: I am willing to spend more money in order to buy products that are sustainable | Y3: I believe it is acceptable to spend extra money for products that are sustainable | Z3: Retailers should be required to take back packaging they sell product in (including cardboard, bubble, wrap or filler, polystyrene.. | AA3: There should be a bottle deposit scheme, with customers reimbursed for taking back milk, juice and water bottles to the retailer or a recycle station | AB3: What is your total household income before tax?Â | AC3: I feel capable of helping solve sustainability issues, e.g. environment, societal problems | AD3: I can contribute to a sustainable future by buying products that are made sustainably | AE3: I feel I can help solve sustainability issues by buying sustainable products | AF3: What I purchase as a consumer has an effect on the nation’s future sustainability | AG3: Each consumer’s behaviour can have a positive effect on society by buying products that are sustainable | AH3: Any individual person can make a difference to the world by choosing products carefully | AI3: I have a good knowledge about sustainability issues | AJ3: I know a great deal about sustainability and sustainability matters | AK3: I know a lot about sustainable products and brands sold in the marketplace
A4: Variable coding: Response Respondent: | B4: Note: To completely answer the full survey a respondent would take a minimum of 240 seconds. 2: New Zealand 3: United States | D4: Minutes | E4: 1: Male 2: Female 3: Gender diverse | F4: 7: Under 18 1: 18-24 2: 25-34 3: 35-44 4: 45-54 5: 55-64 6: 65+ | G4: These numbers don't mean anything per se (nominal data), just that the item was chosen. You can count how many times each item was chosen individually, but analysing combinations within multi-pick questions is problematic! | V4: 1: Not at all 5: Very often 6: Don't know | W4: 1: Not likely 5: Very likely | X4: 1: Strongly disagree 3: Neither disagree nor agree 5: Strongly agree | Y4: 1: Strongly disagree 3: Neither disagree nor agree 5: Strongly agree | Z4: 1: Strongly disagree 3: Neither disagree nor agree 5: Strongly agree | AA4: 1: Strongly disagree 3: Neither disagree nor agree 5: Strongly agree | AB4: 1: Up to $30,000 2: $30,001 - $50,000 3: $50,001 - $70,000 4: $70,001 - $100,000 5: $100,001 - $130,000 6: Over $130,000 7: Would rather not say | AC4: 1: Strongly disagree 3: Neither disagree nor agree 5: Strongly agree | AD4: 1: Strongly disagree 3: Neither disagree nor agree 5: Strongly agree | AE4: 1: Strongly disagree 3: Neither disagree nor agree 5: Strongly agree | AF4: 1: Strongly disagree 3: Neither disagree nor agree 5: Strongly agree | AG4: 1: Strongly disagree 3: Neither disagree nor agree 5: Strongly agree | AH4: 1: Strongly disagree 3: Neither disagree nor agree 5: Strongly agree | AI4: 1: Strongly disagree 3: Neither disagree nor agree 5: Strongly agree | AJ4: 1: Strongly disagree 3: Neither disagree nor agree 5: Strongly agree | AK4: 1: Strongly disagree 3: Neither disagree nor agree 5: Strongly agree
A5: P80 | B5: 14667 | C5: sec | D5: =B5/60 -> 244.45 | E5: 2 | F5: 2 | H5: 2 | J5: 4 | M5: 7 | U5: =COUNT(G5:S5) -> 3 | V5: 3 | W5: 3 | X5: 4 | Y5: 4 | Z5: 3 | AA5: 3 | AB5: 2 | AC5: 3 | AD5: 4 | AE5: 3 | AF5: 3 | AG5: 3 | AH5: 4 | AI5: 3 | AJ5: 3 | AK5: 2
A6: P98 | B6: 4705 | C6: sec | D6: =B6/60 -> 78.416667 | E6: 1 | F6: 3 | I6: 3 | K6: 5 | L6: 6 | M6: 7 | N6: 8 | R6: 12 | S6: 13 | U6: =COUNT(G6:S6) -> 7 | V6: 4 | W6: 3 | X6: 3 | Y6: 3 | Z6: 3 | AA6: 3 | AB6: 7 | AC6: 3 | AD6: 3 | AE6: 3 | AF6: 3 | AG6: 3 | AH6: 3 | AI6: 3 | AJ6: 3 | AK6: 3
A7: P102 | B7: 4705 | C7: sec | D7: =B7/60 -> 78.416667 | E7: 2 | F7: 2 | J7: 4 | L7: 6 | O7: 9 | R7: 12 | U7: =COUNT(G7:S7) -> 4 | V7: 4 | W7: 4 | X7: 2 | Y7: 3 | Z7: 3 | AA7: 4 | AB7: 4 | AC7: 4 | AD7: 3 | AE7: 4 | AF7: 5 | AG7: 4 | AH7: 4 | AI7: 4 | AJ7: 3 | AK7: 4
A8: P42 | B8: 2553 | C8: sec | D8: =B8/60 -> 42.55 | E8: 2 | F8: 5 | H8: 2 | I8: 3 | J8: 4 | L8: 6 | M8: 7 | N8: 8 | O8: 9 | P8: 10 | Q8: 11 | R8: 12 | U8: =COUNT(G8:S8) -> 10 | V8: 6 | W8: 3 | X8: 2 | Y8: 3 | Z8: 5 | AA8: 5 | AB8: 2 | AC8: 3 | AD8: 4 | AE8: 5 | AF8: 4 | AG8: 5 | AH8: 5 | AI8: 2 | AJ8: 2 | AK8: 1
A9: P67 | B9: 2127 | C9: sec | D9: =B9/60 -> 35.45 | E9: 2 | F9: 1 | H9: 2 | I9: 3 | J9: 4 | K9: 5 | L9: 6 | M9: 7 | N9: 8 | Q9: 11 | R9: 12 | S9: 13 | U9: =COUNT(G9:S9) -> 10 | V9: 4 | W9: 4 | X9: 3 | Y9: 3 | Z9: 5 | AA9: 3 | AB9: 2 | AC9: 4 | AD9: 5 | AE9: 4 | AF9: 5 | AG9: 5 | AH9: 5 | AI9: 3 | AJ9: 3 | AK9: 3
A10: P2 | B10: 1861 | C10: sec | D10: =B10/60 -> 31.016667 | E10: 2 | F10: 5 | H10: 2 | I10: 3 | K10: 5 | L10: 6 | N10: 8 | P10: 10 | R10: 12 | U10: =COUNT(G10:S10) -> 7 | V10: 6 | W10: 3 | X10: 3 | Y10: 4 | Z10: 4 | AA10: 4 | AB10: 1 | AC10: 3 | AD10: 4 | AE10: 3 | AF10: 4 | AG10: 4 | AH10: 4 | AI10: 2 | AJ10: 1 | AK10: 2
A11: P40 | B11: 1790 | C11: sec | D11: =B11/60 -> 29.833333 | E11: 2 | F11: 2 | H11: 2 | U11: =COUNT(G11:S11) -> 1 | V11: 5 | W11: 5 | X11: 5 | Y11: 5 | Z11: 5 | AA11: 5 | AB11: 3 | AC11: 5 | AD11: 5 | AE11: 5 | AF11: 5 | AG11: 5 | AH11: 5 | AI11: 5 | AJ11: 5 | AK11: 5
A12: P91 | B12: 1768 | C12: sec | D12: =B12/60 -> 29.466667 | E12: 2 | F12: 3 | H12: 2 | I12: 3 | L12: 6 | M12: 7 | Q12: 11 | U12: =COUNT(G12:S12) -> 5 | V12: 1 | W12: 2 | X12: 2 | Y12: 3 | Z12: 5 | AA12: 5 | AB12: 4 | AC12: 3 | AD12: 3 | AE12: 3 | AF12: 2 | AG12: 3 | AH12: 3 | AI12: 3 | AJ12: 3 | AK12: 2
A13: P59 | B13: 1639 | C13: sec | D13: =B13/60 -> 27.316667 | E13: 2 | F13: 2 | H13: 2 | I13: 3 | K13: 5 | L13: 6 | M13: 7 | P13: 10 | Q13: 11 | R13: 12 | U13: =COUNT(G13:S13) -> 8 | V13: 2 | W13: 4 | X13: 3 | Y13: 4 | Z13: 4 | AA13: 5 | AB13: 3 | AC13: 2 | AD13: 5 | AE13: 5 | AF13: 4 | AG13: 5 | AH13: 5 | AI13: 4 | AJ13: 3 | AK13: 3
A14: P73 | B14: 1636 | C14: sec | D14: =B14/60 -> 27.266667 | E14: 2 | F14: 4 | G14: 1 | H14: 2 | I14: 3 | J14: 4 | K14: 5 | L14: 6 | M14: 7 | N14: 8 | O14: 9 | P14: 10 | Q14: 11 | R14: 12 | S14: 13 | U14: =COUNT(G14:S14) -> 13 | V14: 6 | W14: 5 | X14: 5 | Y14: 5 | Z14: 5 | AA14: 5 | AB14: 2 | AC14: 4 | AD14: 5 | AE14: 4 | AF14: 5 | AG14: 5 | AH14: 5 | AI14: 3 | AJ14: 3 | AK14: 3
A15: P94 | B15: 1582 | C15: sec | D15: =B15/60 -> 26.366667 | E15: 1 | F15: 3 | G15: 1 | J15: 4 | M15: 7 | Q15: 11 | U15: =COUNT(G15:S15) -> 4 | V15: 5 | W15: 5 | X15: 5 | Y15: 5 | Z15: 4 | AA15: 5 | AB15: 1 | AC15: 5 | AD15: 5 | AE15: 5 | AF15: 4 | AG15: 5 | AH15: 5 | AI15: 5 | AJ15: 4 | AK15: 5
A16: P48 | B16: 1572 | C16: sec | D16: =B16/60 -> 26.2 | E16: 2 | F16: 2 | I16: 3 | J16: 4 | K16: 5 | L16: 6 | M16: 7 | P16: 10 | Q16: 11 | R16: 12 | U16: =COUNT(G16:S16) -> 8 | V16: 3 | W16: 4 | X16: 4 | Y16: 4 | Z16: 4 | AA16: 4 | AB16: 5 | AC16: 4 | AD16: 5 | AE16: 5 | AF16: 5 | AG16: 4 | AH16: 4 | AI16: 4 | AJ16: 4 | AK16: 4
A17: P79 | B17: 1506 | C17: sec | D17: =B17/60 -> 25.1 | E17: 2 | F17: 6 | H17: 2 | I17: 3 | K17: 5 | L17: 6 | M17: 7 | N17: 8 | P17: 10 | Q17: 11 | R17: 12 | S17: 13 | U17: =COUNT(G17:S17) -> 10 | V17: 4 | W17: 4 | X17: 4 | Y17: 4 | Z17: 5 | AA17: 5 | AB17: 4 | AC17: 5 | AD17: 5 | AE17: 5 | AF17: 5 | AG17: 3 | AH17: 5 | AI17: 4 | AJ17: 4 | AK17: 4
A18: P54 | B18: 1353 | C18: sec | D18: =B18/60 -> 22.55 | E18: 1 | F18: 2 | H18: 2 | J18: 4 | K18: 5 | L18: 6 | N18: 8 | O18: 9 | P18: 10 | Q18: 11 | R18: 12 | U18: =COUNT(G18:S18) -> 9 | V18: 3 | W18: 1 | X18: 5 | Y18: 1 | Z18: 5 | AA18: 5 | AB18: 3 | AC18: 5 | AD18: 5 | AE18: 1 | AF18: 3 | AG18: 2 | AH18: 1 | AI18: 2 | AJ18: 3 | AK18: 1
A19: P38 | B19: 1316 | C19: sec | D19: =B19/60 -> 21.933333 | E19: 2 | F19: 6 | H19: 2 | I19: 3 | J19: 4 | K19: 5 | L19: 6 | M19: 7 | P19: 10 | Q19: 11 | R19: 12 | U19: =COUNT(G19:S19) -> 9 | V19: 6 | W19: 3 | X19: 3 | Y19: 3 | Z19: 4 | AA19: 5 | AB19: 2 | AC19: 3 | AD19: 3 | AE19: 3 | AF19: 4 | AG19: 4 | AH19: 3 | AI19: 3 | AJ19: 3 | AK19: 3
A20: P65 | B20: 1168 | C20: sec | D20: =B20/60 -> 19.466667 | E20: 2 | F20: 2 | H20: 2 | I20: 3 | K20: 5 | L20: 6 | M20: 7 | N20: 8 | Q20: 11 | R20: 12 | U20: =COUNT(G20:S20) -> 8 | V20: 2 | W20: 2 | X20: 3 | Y20: 3 | Z20: 5 | AA20: 5 | AB20: 5 | AC20: 3 | AD20: 4 | AE20: 3 | AF20: 5 | AG20: 4 | AH20: 4 | AI20: 2 | AJ20: 2 | AK20: 1
A21: P83 | B21: 1155 | C21: sec | D21: =B21/60 -> 19.25 | E21: 2 | F21: 1 | H21: 2 | I21: 3 | K21: 5 | L21: 6 | M21: 7 | N21: 8 | Q21: 11 | R21: 12 | U21: =COUNT(G21:S21) -> 8 | V21: 4 | W21: 4 | X21: 4 | Y21: 4 | Z21: 2 | AA21: 5 | AB21: 4 | AC21: 4 | AD21: 4 | AE21: 4 | AF21: 4 | AG21: 4 | AH21: 4 | AI21: 5 | AJ21: 5 | AK21: 4
A22: P69 | B22: 1126 | C22: sec | D22: =B22/60 -> 18.766667 | E22: 2 | F22: 6 | H22: 2 | I22: 3 | J22: 4 | K22: 5 | L22: 6 | M22: 7 | N22: 8 | P22: 10 | Q22: 11 | R22: 12 | S22: 13 | U22: =COUNT(G22:S22) -> 11 | V22: 6 | W22: 3 | X22: 3 | Y22: 4 | Z22: 3 | AA22: 5 | AB22: 2 | AC22: 5 | AD22: 5 | AE22: 5 | AF22: 5 | AG22: 5 | AH22: 5 | AI22: 4 | AJ22: 4 | AK22: 3
A23: P17 | B23: 1074 | C23: sec | D23: =B23/60 -> 17.9 | E23: 2 | F23: 6 | G23: 1 | H23: 2 | I23: 3 | J23: 4 | K23: 5 | L23: 6 | P23: 10 | Q23: 11 | R23: 12 | U23: =COUNT(G23:S23) -> 9 | V23: 5 | W23: 4 | X23: 4 | Y23: 4 | Z23: 5 | AA23: 5 | AB23: 2 | AC23: 5 | AD23: 5 | AE23: 5 | AF23: 5 | AG23: 5 | AH23: 5 | AI23: 3 | AJ23: 3 | AK23: 3
A24: P18 | B24: 1019 | C24: sec | D24: =B24/60 -> 16.983333 | E24: 2 | F24: 2 | H24: 2 | I24: 3 | K24: 5 | L24: 6 | N24: 8 | U24: =COUNT(G24:S24) -> 5 | V24: 3 | W24: 2 | X24: 3 | Y24: 3 | Z24: 3 | AA24: 3 | AB24: 7 | AC24: 4 | AD24: 3 | AE24: 4 | AF24: 3 | AG24: 1 | AH24: 5 | AI24: 2 | AJ24: 3 | AK24: 2
A25: P15 | B25: 999 | C25: sec | D25: =B25/60 -> 16.65 | E25: 2 | F25: 1 | H25: 2 | I25: 3 | J25: 4 | M25: 7 | O25: 9 | S25: 13 | U25: =COUNT(G25:S25) -> 6 | V25: 3 | W25: 4 | X25: 4 | Y25: 4 | Z25: 3 | AA25: 5 | AB25: 3 | AC25: 5 | AD25: 5 | AE25: 4 | AF25: 5 | AG25: 5 | AH25: 5 | AI25: 3 | AJ25: 2 | AK25: 2
A26: P31 | B26: 970 | C26: sec | D26: =B26/60 -> 16.166667 | E26: 1 | F26: 2 | H26: 2 | K26: 5 | L26: 6 | M26: 7 | N26: 8 | Q26: 11 | U26: =COUNT(G26:S26) -> 6 | V26: 6 | W26: 1 | X26: 1 | Y26: 1 | Z26: 5 | AA26: 5 | AB26: 7 | AC26: 5 | AD26: 5 | AE26: 5 | AF26: 5 | AG26: 5 | AH26: 5 | AI26: 3 | AJ26: 2 | AK26: 2
A27: P11 | B27: 956 | C27: sec | D27: =B27/60 -> 15.933333 | E27: 1 | F27: 2 | G27: 1 | H27: 2 | J27: 4 | L27: 6 | O27: 9 | P27: 10 | U27: =COUNT(G27:S27) -> 6 | V27: 4 | W27: 4 | X27: 4 | Y27: 4 | Z27: 5 | AA27: 2 | AB27: 6 | AC27: 4 | AD27: 3 | AE27: 2 | AF27: 5 | AG27: 2 | AH27: 4 | AI27: 4 | AJ27: 5 | AK27: 5
A28: P8 | B28: 952 | C28: sec | D28: =B28/60 -> 15.866667 | E28: 2 | F28: 2 | H28: 2 | J28: 4 | K28: 5 | L28: 6 | M28: 7 | U28: =COUNT(G28:S28) -> 5 | V28: 4 | W28: 4 | X28: 4 | Y28: 3 | Z28: 5 | AA28: 4 | AB28: 7 | AC28: 4 | AD28: 4 | AE28: 4 | AF28: 4 | AG28: 4 | AH28: 4 | AI28: 4 | AJ28: 4 | AK28: 4
A29: P41 | B29: 940 | C29: sec | D29: =B29/60 -> 15.666667 | E29: 2 | F29: 2 | H29: 2 | J29: 4 | L29: 6 | M29: 7 | O29: 9 | U29: =COUNT(G29:S29) -> 5 | V29: 4 | W29: 4 | X29: 4 | Y29: 3 | Z29: 3 | AA29: 5 | AB29: 7 | AC29: 3 | AD29: 5 | AE29: 5 | AF29: 4 | AG29: 5 | AH29: 4 | AI29: 3 | AJ29: 3 | AK29: 3
A30: P93 | B30: 934 | C30: sec | D30: =B30/60 -> 15.566667 | E30: 1 | F30: 2 | Q30: 11 | U30: =COUNT(G30:S30) -> 1 | V30: 4 | W30: 3 | X30: 3 | Y30: 3 | Z30: 3 | AA30: 3 | AB30: 4 | AC30: 3 | AD30: 3 | AE30: 3 | AF30: 3 | AG30: 3 | AH30: 3 | AI30: 3 | AJ30: 3 | AK30: 3
A31: P78 | B31: 920 | C31: sec | D31: =B31/60 -> 15.333333 | E31: 2 | F31: 1 | H31: 2 | I31: 3 | K31: 5 | L31: 6 | M31: 7 | N31: 8 | Q31: 11 | U31: =COUNT(G31:S31) -> 7 | V31: 4 | W31: 4 | X31: 4 | Y31: 5 | Z31: 4 | AA31: 4 | AB31: 3 | AC31: 3 | AD31: 4 | AE31: 4 | AF31: 5 | AG31: 4 | AH31: 4 | AI31: 4 | AJ31: 4 | AK31: 4
A32: P14 | B32: 883 | C32: sec | D32: =B32/60 -> 14.716667 | E32: 1 | F32: 1 | H32: 2 | N32: 8 | U32: =COUNT(G32:S32) -> 2 | V32: 2 | W32: 3 | X32: 3 | Y32: 3 | Z32: 4 | AA32: 5 | AB32: 3 | AC32: 3 | AD32: 3 | AE32: 3 | AF32: 3 | AG32: 3 | AH32: 4 | AI32: 4 | AJ32: 3 | AK32: 2
A33: P51 | B33: 878 | C33: sec | D33: =B33/60 -> 14.633333 | E33: 2 | F33: 6 | H33: 2 | L33: 6 | U33: =COUNT(G33:S33) -> 2 | V33: 6 | W33: 3 | X33: 3 | Y33: 3 | Z33: 3 | AA33: 4 | AB33: 6 | AC33: 2 | AD33: 3 | AE33: 4 | AF33: 3 | AG33: 4 | AH33: 3 | AI33: 1 | AJ33: 1 | AK33: 1
A34: P77 | B34: 876 | C34: sec | D34: =B34/60 -> 14.6 | E34: 2 | F34: 6 | G34: 1 | J34: 4 | U34: =COUNT(G34:S34) -> 2 | V34: 5 | W34: 3 | X34: 3 | Y34: 3 | Z34: 3 | AA34: 4 | AB34: 1 | AC34: 3 | AD34: 3 | AE34: 3 | AF34: 3 | AG34: 3 | AH34: 4 | AI34: 2 | AJ34: 2 | AK34: 2
A35: P24 | B35: 864 | C35: sec | D35: =B35/60 -> 14.4 | E35: 1 | F35: 5 | G35: 1 | U35: =COUNT(G35:S35) -> 1 | V35: 5 | W35: 4 | X35: 4 | Y35: 4 | Z35: 3 | AA35: 4 | AB35: 4 | AC35: 4 | AD35: 5 | AE35: 4 | AF35: 4 | AG35: 4 | AH35: 4 | AI35: 4 | AJ35: 4 | AK35: 4
A36: P57 | B36: 824 | C36: sec | D36: =B36/60 -> 13.733333 | E36: 2 | F36: 2 | H36: 2 | I36: 3 | K36: 5 | L36: 6 | M36: 7 | N36: 8 | R36: 12 | U36: =COUNT(G36:S36) -> 7 | V36: 3 | W36: 3 | X36: 3 | Y36: 3 | Z36: 4 | AA36: 5 | AB36: 7 | AC36: 4 | AD36: 4 | AE36: 3 | AF36: 4 | AG36: 4 | AH36: 4 | AI36: 4 | AJ36: 4 | AK36: 4
A37: P3 | B37: 821 | C37: sec | D37: =B37/60 -> 13.683333 | E37: 2 | F37: 4 | H37: 2 | M37: 7 | N37: 8 | Q37: 11 | R37: 12 | U37: =COUNT(G37:S37) -> 5 | V37: 4 | W37: 5 | X37: 5 | Y37: 5 | Z37: 5 | AA37: 5 | AB37: 1 | AC37: 5 | AD37: 5 | AE37: 5 | AF37: 5 | AG37: 5 | AH37: 5 | AI37: 3 | AJ37: 3 | AK37: 3
A38: P21 | B38: 821 | C38: sec | D38: =B38/60 -> 13.683333 | E38: 2 | F38: 2 | H38: 2 | I38: 3 | J38: 4 | L38: 6 | N38: 8 | P38: 10 | U38: =COUNT(G38:S38) -> 6 | V38: 4 | W38: 4 | X38: 4 | Y38: 4 | Z38: 4 | AA38: 4 | AB38: 5 | AC38: 3 | AD38: 4 | AE38: 3 | AF38: 3 | AG38: 4 | AH38: 4 | AI38: 3 | AJ38: 3 | AK38: 3
A39: P53 | B39: 800 | C39: sec | D39: =B39/60 -> 13.333333 | E39: 2 | F39: 2 | H39: 2 | J39: 4 | L39: 6 | M39: 7 | N39: 8 | O39: 9 | U39: =COUNT(G39:S39) -> 6 | V39: 6 | W39: 4 | X39: 3 | Y39: 4 | Z39: 5 | AA39: 4 | AB39: 2 | AC39: 2 | AD39: 3 | AE39: 2 | AF39: 3 | AG39: 3 | AH39: 3 | AI39: 3 | AJ39: 4 | AK39: 3
A40: P82 | B40: 786 | C40: sec | D40: =B40/60 -> 13.1 | E40: 2 | F40: 2 | T40: 14 | U40: =COUNT(G40:S40) -> 0 | V40: 4 | W40: 3 | X40: 2 | Y40: 2 | Z40: 2 | AA40: 4 | AB40: 3 | AC40: 2 | AD40: 4 | AE40: 3 | AF40: 4 | AG40: 3 | AH40: 4 | AI40: 2 | AJ40: 1 | AK40: 2
A41: P5 | B41: 785 | C41: sec | D41: =B41/60 -> 13.083333 | E41: 1 | F41: 4 | H41: 2 | I41: 3 | K41: 5 | L41: 6 | M41: 7 | N41: 8 | P41: 10 | S41: 13 | U41: =COUNT(G41:S41) -> 8 | V41: 6 | W41: 3 | X41: 3 | Y41: 3 | Z41: 5 | AA41: 5 | AB41: 1 | AC41: 3 | AD41: 4 | AE41: 4 | AF41: 3 | AG41: 4 | AH41: 4 | AI41: 3 | AJ41: 2 | AK41: 2
A42: P50 | B42: 777 | C42: sec | D42: =B42/60 -> 12.95 | E42: 2 | F42: 5 | H42: 2 | I42: 3 | J42: 4 | L42: 6 | Q42: 11 | R42: 12 | U42: =COUNT(G42:S42) -> 6 | V42: 6 | W42: 1 | X42: 1 | Y42: 1 | Z42: 4 | AA42: 5 | AB42: 2 | AC42: 3 | AD42: 4 | AE42: 4 | AF42: 4 | AG42: 3 | AH42: 4 | AI42: 1 | AJ42: 1 | AK42: 1
A43: P66 | B43: 771 | C43: sec | D43: =B43/60 -> 12.85 | E43: 2 | F43: 3 | G43: 1 | J43: 4 | K43: 5 | R43: 12 | U43: =COUNT(G43:S43) -> 4 | V43: 4 | W43: 5 | X43: 3 | Y43: 4 | Z43: 4 | AA43: 4 | AB43: 6 | AC43: 5 | AD43: 2 | AE43: 2 | AF43: 3 | AG43: 4 | AH43: 4 | AI43: 3 | AJ43: 2 | AK43: 4
A44: P63 | B44: 760 | C44: sec | D44: =B44/60 -> 12.666667 | E44: 2 | F44: 2 | H44: 2 | I44: 3 | J44: 4 | K44: 5 | L44: 6 | M44: 7 | N44: 8 | P44: 10 | Q44: 11 | R44: 12 | S44: 13 | U44: =COUNT(G44:S44) -> 11 | V44: 4 | W44: 3 | X44: 3 | Y44: 5 | Z44: 4 | AA44: 5 | AB44: 6 | AC44: 3 | AD44: 3 | AE44: 4 | AF44: 4 | AG44: 4 | AH44: 4 | AI44: 2 | AJ44: 2 | AK44: 1
A45: P4 | B45: 759 | C45: sec | D45: =B45/60 -> 12.65 | E45: 1 | F45: 4 | H45: 2 | K45: 5 | L45: 6 | U45: =COUNT(G45:S45) -> 3 | V45: 6 | W45: 3 | X45: 3 | Y45: 3 | Z45: 3 | AA45: 3 | AB45: 6 | AC45: 3 | AD45: 3 | AE45: 3 | AF45: 3 | AG45: 3 | AH45: 3 | AI45: 2 | AJ45: 2 | AK45: 2
A46: P76 | B46: 753 | C46: sec | D46: =B46/60 -> 12.55 | E46: 2 | F46: 4 | G46: 1 | H46: 2 | I46: 3 | J46: 4 | K46: 5 | L46: 6 | M46: 7 | N46: 8 | O46: 9 | P46: 10 | Q46: 11 | R46: 12 | S46: 13 | U46: =COUNT(G46:S46) -> 13 | V46: 4 | W46: 5 | X46: 5 | Y46: 5 | Z46: 5 | AA46: 5 | AB46: 6 | AC46: 5 | AD46: 5 | AE46: 5 | AF46: 5 | AG46: 5 | AH46: 5 | AI46: 4 | AJ46: 4 | AK46: 4
A47: P27 | B47: 740 | C47: sec | D47: =B47/60 -> 12.333333 | E47: 2 | F47: 2 | P47: 10 | R47: 12 | U47: =COUNT(G47:S47) -> 2 | V47: 4 | W47: 3 | X47: 3 | Y47: 3 | Z47: 3 | AA47: 3 | AB47: 7 | AC47: 3 | AD47: 3 | AE47: 4 | AF47: 3 | AG47: 3 | AH47: 4 | AI47: 3 | AJ47: 3 | AK47: 3
A48: P30 | B48: 737 | C48: sec | D48: =B48/60 -> 12.283333 | E48: 2 | F48: 5 | L48: 6 | U48: =COUNT(G48:S48) -> 1 | V48: 6 | W48: 1 | X48: 1 | Y48: 1 | Z48: 3 | AA48: 5 | AB48: 4 | AC48: 1 | AD48: 4 | AE48: 4 | AF48: 2 | AG48: 4 | AH48: 4 | AI48: 1 | AJ48: 1 | AK48: 1
A49: P72 | B49: 734 | C49: sec | D49: =B49/60 -> 12.233333 | E49: 2 | F49: 1 | G49: 1 | H49: 2 | I49: 3 | J49: 4 | K49: 5 | L49: 6 | M49: 7 | N49: 8 | O49: 9 | P49: 10 | Q49: 11 | R49: 12 | S49: 13 | U49: =COUNT(G49:S49) -> 13 | V49: 5 | W49: 5 | X49: 5 | Y49: 5 | Z49: 4 | AA49: 4 | AB49: 7 | AC49: 4 | AD49: 5 | AE49: 5 | AF49: 5 | AG49: 5 | AH49: 5 | AI49: 4 | AJ49: 4 | AK49: 4
A50: P36 | B50: 714 | C50: sec | D50: =B50/60 -> 11.9 | E50: 2 | F50: 5 | H50: 2 | I50: 3 | M50: 7 | U50: =COUNT(G50:S50) -> 3 | V50: 3 | W50: 2 | X50: 2 | Y50: 3 | Z50: 5 | AA50: 5 | AB50: 2 | AC50: 4 | AD50: 4 | AE50: 3 | AF50: 3 | AG50: 4 | AH50: 5 | AI50: 2 | AJ50: 2 | AK50: 2
A51: P52 | B51: 708 | C51: sec | D51: =B51/60 -> 11.8 | E51: 2 | F51: 2 | G51: 1 | H51: 2 | I51: 3 | J51: 4 | K51: 5 | L51: 6 | M51: 7 | O51: 9 | P51: 10 | Q51: 11 | R51: 12 | U51: =COUNT(G51:S51) -> 11 | V51: 3 | W51: 4 | X51: 4 | Y51: 4 | Z51: 4 | AA51: 4 | AB51: 3 | AC51: 4 | AD51: 4 | AE51: 4 | AF51: 4 | AG51: 4 | AH51: 4 | AI51: 4 | AJ51: 4 | AK51: 3
A52: P7 | B52: 706 | C52: sec | D52: =B52/60 -> 11.766667 | E52: 2 | F52: 6 | H52: 2 | J52: 4 | M52: 7 | P52: 10 | R52: 12 | U52: =COUNT(G52:S52) -> 5 | V52: 6 | W52: 3 | X52: 3 | Y52: 2 | Z52: 4 | AA52: 5 | AB52: 1 | AC52: 3 | AD52: 4 | AE52: 3 | AF52: 3 | AG52: 3 | AH52: 4 | AI52: 1 | AJ52: 1 | AK52: 2
A53: P32 | B53: 688 | C53: sec | D53: =B53/60 -> 11.466667 | E53: 1 | F53: 1 | H53: 2 | I53: 3 | L53: 6 | U53: =COUNT(G53:S53) -> 3 | V53: 6 | W53: 3 | X53: 2 | Y53: 3 | Z53: 4 | AA53: 4 | AB53: 3 | AC53: 4 | AD53: 5 | AE53: 5 | AF53: 4 | AG53: 5 | AH53: 4 | AI53: 2 | AJ53: 2 | AK53: 1
A54: P45 | B54: 687 | C54: sec | D54: =B54/60 -> 11.45 | E54: 2 | F54: 6 | T54: 14 | U54: =COUNT(G54:S54) -> 0 | V54: 6 | W54: 3 | X54: 3 | Y54: 3 | Z54: 1 | AA54: 1 | AB54: 1 | AC54: 3 | AD54: 3 | AE54: 3 | AF54: 3 | AG54: 3 | AH54: 3 | AI54: 2 | AJ54: 2 | AK54: 2
A55: P99 | B55: 687 | C55: sec | D55: =B55/60 -> 11.45 | E55: 2 | F55: 2 | H55: 2 | L55: 6 | R55: 12 | S55: 13 | U55: =COUNT(G55:S55) -> 4 | V55: 4 | W55: 4 | X55: 4 | Y55: 4 | Z55: 4 | AA55: 4 | AB55: 7 | AC55: 4 | AD55: 4 | AE55: 4 | AF55: 4 | AG55: 4 | AH55: 4 | AI55: 4 | AJ55: 4 | AK55: 4
A56: P103 | B56: 687 | C56: sec | D56: =B56/60 -> 11.45 | E56: 2 | F56: 1 | G56: 1 | K56: 5 | P56: 10 | U56: =COUNT(G56:S56) -> 3 | V56: 5 | W56: 5 | X56: 4 | Y56: 5 | Z56: 4 | AA56: 4 | AB56: 3 | AC56: 4 | AD56: 4 | AE56: 4 | AF56: 4 | AG56: 4 | AH56: 5 | AI56: 4 | AJ56: 5 | AK56: 4
A57: P22 | B57: 685 | C57: sec | D57: =B57/60 -> 11.416667 | E57: 2 | F57: 2 | H57: 2 | I57: 3 | J57: 4 | K57: 5 | L57: 6 | M57: 7 | N57: 8 | P57: 10 | Q57: 11 | R57: 12 | U57: =COUNT(G57:S57) -> 10 | V57: 6 | W57: 4 | X57: 4 | Y57: 4 | Z57: 4 | AA57: 3 | AB57: 3 | AC57: 3 | AD57: 4 | AE57: 4 | AF57: 3 | AG57: 4 | AH57: 5 | AI57: 3 | AJ57: 3 | AK57: 3
A58: P92 | B58: 670 | C58: sec | D58: =B58/60 -> 11.166667 | E58: 1 | F58: 2 | H58: 2 | J58: 4 | K58: 5 | L58: 6 | M58: 7 | N58: 8 | O58: 9 | Q58: 11 | R58: 12 | U58: =COUNT(G58:S58) -> 9 | V58: 5 | W58: 3 | X58: 3 | Y58: 4 | Z58: 4 | AA58: 4 | AB58: 1 | AC58: 5 | AD58: 5 | AE58: 5 | AF58: 5 | AG58: 5 | AH58: 4 | AI58: 4 | AJ58: 4 | AK58: 4
A59: P49 | B59: 665 | C59: sec | D59: =B59/60 -> 11.083333 | E59: 1 | F59: 2 | M59: 7 | N59: 8 | O59: 9 | P59: 10 | R59: 12 | S59: 13 | U59: =COUNT(G59:S59) -> 6 | V59: 4 | W59: 3 | X59: 3 | Y59: 4 | Z59: 4 | AA59: 3 | AB59: 4 | AC59: 4 | AD59: 4 | AE59: 3 | AF59: 4 | AG59: 2 | AH59: 4 | AI59: 5 | AJ59: 4 | AK59: 4
A60: P25 | B60: 632 | C60: sec | D60: =B60/60 -> 10.533333 | E60: 2 | F60: 2 | H60: 2 | I60: 3 | J60: 4 | K60: 5 | L60: 6 | M60: 7 | N60: 8 | P60: 10 | Q60: 11 | R60: 12 | S60: 13 | U60: =COUNT(G60:S60) -> 11 | V60: 5 | W60: 5 | X60: 5 | Y60: 5 | Z60: 3 | AA60: 5 | AB60: 5 | AC60: 3 | AD60: 5 | AE60: 5 | AF60: 5 | AG60: 5 | AH60: 4 | AI60: 3 | AJ60: 3 | AK60: 4
A61: P90 | B61: 632 | C61: sec | D61: =B61/60 -> 10.533333 | E61: 2 | F61: 2 | H61: 2 | L61: 6 | U61: =COUNT(G61:S61) -> 2 | V61: 6 | W61: 2 | X61: 2 | Y61: 4 | Z61: 5 | AA61: 5 | AB61: 5 | AC61: 2 | AD61: 4 | AE61: 2 | AF61: 4 | AG61: 5 | AH61: 5 | AI61: 1 | AJ61: 2 | AK61: 1
A62: P46 | B62: 627 | C62: sec | D62: =B62/60 -> 10.45 | E62: 2 | F62: 2 | H62: 2 | I62: 3 | J62: 4 | K62: 5 | L62: 6 | M62: 7 | Q62: 11 | R62: 12 | U62: =COUNT(G62:S62) -> 8 | V62: 5 | W62: 3 | X62: 3 | Y62: 3 | Z62: 3 | AA62: 5 | AB62: 2 | AC62: 5 | AD62: 5 | AE62: 5 | AF62: 5 | AG62: 5 | AH62: 5 | AI62: 3 | AJ62: 3 | AK62: 3
A63: P89 | B63: 624 | C63: sec | D63: =B63/60 -> 10.4 | E63: 1 | F63: 5 | H63: 2 | J63: 4 | M63: 7 | U63: =COUNT(G63:S63) -> 3 | V63: 4 | W63: 3 | X63: 1 | Y63: 2 | Z63: 3 | AA63: 2 | AB63: 7 | AC63: 1 | AD63: 2 | AE63: 1 | AF63: 2 | AG63: 2 | AH63: 3 | AI63: 2 | AJ63: 4 | AK63: 2
A64: P29 | B64: 618 | C64: sec | D64: =B64/60 -> 10.3 | E64: 2 | F64: 2 | H64: 2 | I64: 3 | K64: 5 | L64: 6 | M64: 7 | N64: 8 | Q64: 11 | R64: 12 | U64: =COUNT(G64:S64) -> 8 | V64: 5 | W64: 3 | X64: 3 | Y64: 3 | Z64: 3 | AA64: 4 | AB64: 2 | AC64: 3 | AD64: 3 | AE64: 3 | AF64: 4 | AG64: 3 | AH64: 4 | AI64: 3 | AJ64: 3 | AK64: 3
A65: P34 | B65: 613 | C65: sec | D65: =B65/60 -> 10.216667 | E65: 2 | F65: 1 | H65: 2 | L65: 6 | M65: 7 | P65: 10 | U65: =COUNT(G65:S65) -> 4 | V65: 4 | W65: 5 | X65: 4 | Y65: 5 | Z65: 4 | AA65: 5 | AB65: 7 | AC65: 3 | AD65: 4 | AE65: 4 | AF65: 5 | AG65: 4 | AH65: 5 | AI65: 4 | AJ65: 4 | AK65: 3
A66: P10 | B66: 598 | C66: sec | D66: =B66/60 -> 9.9666667 | E66: 1 | F66: 1 | H66: 2 | I66: 3 | K66: 5 | L66: 6 | M66: 7 | Q66: 11 | R66: 12 | U66: =COUNT(G66:S66) -> 7 | V66: 4 | W66: 4 | X66: 4 | Y66: 5 | Z66: 2 | AA66: 5 | AB66: 3 | AC66: 3 | AD66: 5 | AE66: 4 | AF66: 5 | AG66: 4 | AH66: 4 | AI66: 4 | AJ66: 4 | AK66: 2
A67: P43 | B67: 598 | C67: sec | D67: =B67/60 -> 9.9666667 | E67: 2 | F67: 1 | I67: 3 | J67: 4 | K67: 5 | L67: 6 | M67: 7 | N67: 8 | Q67: 11 | U67: =COUNT(G67:S67) -> 7 | V67: 3 | W67: 4 | X67: 4 | Y67: 4 | Z67: 3 | AA67: 4 | AB67: 1 | AC67: 2 | AD67: 4 | AE67: 5 | AF67: 4 | AG67: 5 | AH67: 5 | AI67: 3 | AJ67: 4 | AK67: 4
A68: P28 | B68: 588 | C68: sec | D68: =B68/60 -> 9.8 | E68: 2 | F68: 2 | H68: 2 | J68: 4 | L68: 6 | M68: 7 | N68: 8 | O68: 9 | P68: 10 | S68: 13 | U68: =COUNT(G68:S68) -> 8 | V68: 6 | W68: 4 | X68: 4 | Y68: 3 | Z68: 5 | AA68: 5 | AB68: 3 | AC68: 4 | AD68: 4 | AE68: 4 | AF68: 4 | AG68: 4 | AH68: 4 | AI68: 3 | AJ68: 3 | AK68: 2
A69: P33 | B69: 587 | C69: sec | D69: =B69/60 -> 9.7833333 | E69: 2 | F69: 2 | Q69: 11 | U69: =COUNT(G69:S69) -> 1 | V69: 5 | W69: 4 | X69: 4 | Y69: 4 | Z69: 3 | AA69: 4 | AB69: 3 | AC69: 4 | AD69: 4 | AE69: 4 | AF69: 4 | AG69: 3 | AH69: 4 | AI69: 4 | AJ69: 4 | AK69: 4
A70: P85 | B70: 572 | C70: sec | D70: =B70/60 -> 9.5333333 | E70: 2 | F70: 2 | H70: 2 | J70: 4 | K70: 5 | L70: 6 | M70: 7 | O70: 9 | P70: 10 | Q70: 11 | R70: 12 | U70: =COUNT(G70:S70) -> 9 | V70: 4 | W70: 4 | X70: 4 | Y70: 4 | Z70: 5 | AA70: 5 | AB70: 3 | AC70: 5 | AD70: 4 | AE70: 3 | AF70: 5 | AG70: 5 | AH70: 4 | AI70: 3 | AJ70: 3 | AK70: 4
A71: P37 | B71: 544 | C71: sec | D71: =B71/60 -> 9.0666667 | E71: 2 | F71: 2 | H71: 2 | L71: 6 | U71: =COUNT(G71:S71) -> 2 | V71: 6 | W71: 2 | X71: 1 | Y71: 3 | Z71: 5 | AA71: 5 | AB71: 3 | AC71: 2 | AD71: 4 | AE71: 4 | AF71: 3 | AG71: 4 | AH71: 3 | AI71: 2 | AJ71: 2 | AK71: 2
A72: P20 | B72: 516 | C72: sec | D72: =B72/60 -> 8.6 | E72: 2 | F72: 4 | H72: 2 | I72: 3 | O72: 9 | U72: =COUNT(G72:S72) -> 3 | V72: 6 | W72: 4 | X72: 3 | Y72: 4 | Z72: 4 | AA72: 4 | AB72: 7 | AC72: 3 | AD72: 3 | AE72: 3 | AF72: 3 | AG72: 3 | AH72: 3 | AI72: 3 | AJ72: 3 | AK72: 3
A73: P56 | B73: 497 | C73: sec | D73: =B73/60 -> 8.2833333 | E73: 2 | F73: 1 | Q73: 11 | R73: 12 | U73: =COUNT(G73:S73) -> 2 | V73: 5 | W73: 4 | X73: 3 | Y73: 4 | Z73: 4 | AA73: 4 | AB73: 4 | AC73: 4 | AD73: 4 | AE73: 4 | AF73: 4 | AG73: 4 | AH73: 4 | AI73: 4 | AJ73: 4 | AK73: 4
A74: P96 | B74: 483 | C74: sec | D74: =B74/60 -> 8.05 | E74: 1 | F74: 3 | J74: 4 | O74: 9 | R74: 12 | U74: =COUNT(G74:S74) -> 3 | V74: 3 | W74: 3 | X74: 3 | Y74: 3 | Z74: 4 | AA74: 3 | AB74: 7 | AC74: 4 | AD74: 4 | AE74: 4 | AF74: 4 | AG74: 3 | AH74: 4 | AI74: 4 | AJ74: 3 | AK74: 4
A75: P71 | B75: 480 | C75: sec | D75: =B75/60 -> 8 | E75: 1 | F75: 6 | H75: 2 | J75: 4 | L75: 6 | N75: 8 | O75: 9 | P75: 10 | Q75: 11 | R75: 12 | S75: 13 | U75: =COUNT(G75:S75) -> 9 | V75: 3 | W75: 5 | X75: 4 | Y75: 5 | Z75: 2 | AA75: 3 | AB75: 7 | AC75: 4 | AD75: 4 | AE75: 5 | AF75: 4 | AG75: 4 | AH75: 5 | AI75: 3 | AJ75: 2 | AK75: 2
A76: P97 | B76: 464 | C76: sec | D76: =B76/60 -> 7.7333333 | E76: 1 | F76: 2 | J76: 4 | S76: 13 | U76: =COUNT(G76:S76) -> 2 | V76: 1 | W76: 2 | X76: 2 | Y76: 4 | Z76: 4 | AA76: 5 | AB76: 6 | AC76: 2 | AD76: 4 | AE76: 2 | AF76: 2 | AG76: 3 | AH76: 2 | AI76: 2 | AJ76: 2 | AK76: 1
A77: P101 | B77: 464 | C77: sec | D77: =B77/60 -> 7.7333333 | E77: 1 | F77: 2 | L77: 6 | M77: 7 | Q77: 11 | U77: =COUNT(G77:S77) -> 3 | V77: 3 | W77: 4 | X77: 3 | Y77: 4 | Z77: 3 | AA77: 3 | AB77: 1 | AC77: 3 | AD77: 4 | AE77: 2 | AF77: 2 | AG77: 4 | AH77: 2 | AI77: 4 | AJ77: 3 | AK77: 2
A78: P47 | B78: 463 | C78: sec | D78: =B78/60 -> 7.7166667 | E78: 1 | F78: 2 | H78: 2 | L78: 6 | M78: 7 | P78: 10 | R78: 12 | U78: =COUNT(G78:S78) -> 5 | V78: 3 | W78: 3 | X78: 1 | Y78: 4 | Z78: 4 | AA78: 5 | AB78: 1 | AC78: 3 | AD78: 4 | AE78: 1 | AF78: 1 | AG78: 2 | AH78: 1 | AI78: 4 | AJ78: 2 | AK78: 2
A79: P88 | B79: 463 | C79: sec | D79: =B79/60 -> 7.7166667 | E79: 2 | F79: 2 | G79: 1 | H79: 2 | I79: 3 | J79: 4 | K79: 5 | L79: 6 | M79: 7 | N79: 8 | O79: 9 | P79: 10 | Q79: 11 | R79: 12 | S79: 13 | U79: =COUNT(G79:S79) -> 13 | V79: 4 | W79: 5 | X79: 5 | Y79: 5 | Z79: 5 | AA79: 5 | AB79: 3 | AC79: 3 | AD79: 4 | AE79: 4 | AF79: 5 | AG79: 5 | AH79: 4 | AI79: 2 | AJ79: 2 | AK79: 1
A80: P12 | B80: 457 | C80: sec | D80: =B80/60 -> 7.6166667 | E80: 2 | F80: 1 | H80: 2 | I80: 3 | K80: 5 | L80: 6 | N80: 8 | O80: 9 | S80: 13 | U80: =COUNT(G80:S80) -> 7 | V80: 6 | W80: 4 | X80: 4 | Y80: 5 | Z80: 4 | AA80: 5 | AB80: 7 | AC80: 3 | AD80: 4 | AE80: 2 | AF80: 4 | AG80: 4 | AH80: 4 | AI80: 2 | AJ80: 2 | AK80: 3
A81: P9 | B81: 456 | C81: sec | D81: =B81/60 -> 7.6 | E81: 2 | F81: 5 | H81: 2 | I81: 3 | J81: 4 | K81: 5 | L81: 6 | M81: 7 | N81: 8 | O81: 9 | P81: 10 | Q81: 11 | R81: 12 | U81: =COUNT(G81:S81) -> 11 | V81: 3 | W81: 2 | X81: 2 | Y81: 3 | Z81: 3 | AA81: 4 | AB81: 3 | AC81: 4 | AD81: 4 | AE81: 4 | AF81: 4 | AG81: 4 | AH81: 4 | AI81: 2 | AJ81: 2 | AK81: 2
A82: P70 | B82: 449 | C82: sec | D82: =B82/60 -> 7.4833333 | E82: 1 | F82: 2 | H82: 2 | I82: 3 | J82: 4 | K82: 5 | L82: 6 | M82: 7 | N82: 8 | P82: 10 | Q82: 11 | R82: 12 | U82: =COUNT(G82:S82) -> 10 | V82: 3 | W82: 5 | X82: 5 | Y82: 4 | Z82: 5 | AA82: 5 | AB82: 4 | AC82: 4 | AD82: 5 | AE82: 5 | AF82: 5 | AG82: 5 | AH82: 5 | AI82: 5 | AJ82: 5 | AK82: 4
A83: P44 | B83: 448 | C83: sec | D83: =B83/60 -> 7.4666667 | E83: 2 | F83: 2 | H83: 2 | J83: 4 | K83: 5 | L83: 6 | P83: 10 | Q83: 11 | R83: 12 | U83: =COUNT(G83:S83) -> 7 | V83: 5 | W83: 4 | X83: 4 | Y83: 5 | Z83: 4 | AA83: 5 | AB83: 3 | AC83: 3 | AD83: 4 | AE83: 4 | AF83: 5 | AG83: 4 | AH83: 4 | AI83: 4 | AJ83: 3 | AK83: 3
A84: P68 | B84: 447 | C84: sec | D84: =B84/60 -> 7.45 | E84: 2 | F84: 2 | H84: 2 | I84: 3 | J84: 4 | K84: 5 | L84: 6 | M84: 7 | N84: 8 | Q84: 11 | R84: 12 | U84: =COUNT(G84:S84) -> 9 | V84: 5 | W84: 3 | X84: 3 | Y84: 3 | Z84: 5 | AA84: 5 | AB84: 1 | AC84: 5 | AD84: 5 | AE84: 5 | AF84: 5 | AG84: 5 | AH84: 5 | AI84: 4 | AJ84: 4 | AK84: 4
A85: P87 | B85: 445 | C85: sec | D85: =B85/60 -> 7.4166667 | E85: 2 | F85: 5 | H85: 2 | J85: 4 | K85: 5 | L85: 6 | M85: 7 | N85: 8 | P85: 10 | Q85: 11 | R85: 12 | U85: =COUNT(G85:S85) -> 9 | V85: 3 | W85: 3 | X85: 3 | Y85: 3 | Z85: 3 | AA85: 4 | AB85: 7 | AC85: 3 | AD85: 4 | AE85: 3 | AF85: 4 | AG85: 4 | AH85: 4 | AI85: 3 | AJ85: 2 | AK85: 2
A86: P35 | B86: 442 | C86: sec | D86: =B86/60 -> 7.3666667 | E86: 2 | F86: 1 | L86: 6 | M86: 7 | Q86: 11 | U86: =COUNT(G86:S86) -> 3 | V86: 6 | W86: 4 | X86: 4 | Y86: 3 | Z86: 3 | AA86: 3 | AB86: 1 | AC86: 4 | AD86: 4 | AE86: 4 | AF86: 3 | AG86: 4 | AH86: 4 | AI86: 2 | AJ86: 2 | AK86: 2
A87: P100 | B87: 441 | C87: sec | D87: =B87/60 -> 7.35 | E87: 1 | F87: 2 | H87: 2 | I87: 3 | L87: 6 | U87: =COUNT(G87:S87) -> 3 | V87: 3 | W87: 2 | X87: 2 | Y87: 2 | Z87: 4 | AA87: 4 | AB87: 5 | AC87: 3 | AD87: 4 | AE87: 2 | AF87: 4 | AG87: 4 | AH87: 5 | AI87: 2 | AJ87: 3 | AK87: 2
A88: P104 | B88: 441 | C88: sec | D88: =B88/60 -> 7.35 | E88: 1 | F88: 2 | H88: 2 | J88: 4 | K88: 5 | L88: 6 | M88: 7 | S88: 13 | U88: =COUNT(G88:S88) -> 6 | V88: 5 | W88: 3 | X88: 4 | Y88: 3 | Z88: 5 | AA88: 5 | AB88: 7 | AC88: 5 | AD88: 5 | AE88: 5 | AF88: 5 | AG88: 5 | AH88: 5 | AI88: 4 | AJ88: 4 | AK88: 3
A89: P62 | B89: 436 | C89: sec | D89: =B89/60 -> 7.2666667 | E89: 2 | F89: 1 | P89: 10 | U89: =COUNT(G89:S89) -> 1 | V89: 3 | W89: 3 | X89: 3 | Y89: 3 | Z89: 3 | AA89: 3 | AB89: 1 | AC89: 3 | AD89: 3 | AE89: 3 | AF89: 3 | AG89: 3 | AH89: 3 | AI89: 3 | AJ89: 3 | AK89: 3
A90: P84 | B90: 432 | C90: sec | D90: =B90/60 -> 7.2 | E90: 1 | F90: 2 | G90: 1 | J90: 4 | P90: 10 | U90: =COUNT(G90:S90) -> 3 | V90: 5 | W90: 5 | X90: 4 | Y90: 5 | Z90: 4 | AA90: 5 | AB90: 3 | AC90: 4 | AD90: 5 | AE90: 5 | AF90: 5 | AG90: 4 | AH90: 5 | AI90: 5 | AJ90: 5 | AK90: 4
A91: P6 | B91: 429 | C91: sec | D91: =B91/60 -> 7.15 | E91: 2 | F91: 2 | H91: 2 | J91: 4 | M91: 7 | U91: =COUNT(G91:S91) -> 3 | V91: 2 | W91: 3 | X91: 3 | Y91: 4 | Z91: 4 | AA91: 5 | AB91: 4 | AC91: 3 | AD91: 3 | AE91: 4 | AF91: 4 | AG91: 4 | AH91: 4 | AI91: 3 | AJ91: 3 | AK91: 3
A92: P74 | B92: 420 | C92: sec | D92: =B92/60 -> 7 | E92: 2 | F92: 2 | H92: 2 | U92: =COUNT(G92:S92) -> 1 | V92: 6 | W92: 3 | X92: 3 | Y92: 4 | Z92: 4 | AA92: 4 | AB92: 5 | AC92: 2 | AD92: 4 | AE92: 4 | AF92: 4 | AG92: 4 | AH92: 4 | AI92: 2 | AJ92: 2 | AK92: 3
A93: P26 | B93: 409 | C93: sec | D93: =B93/60 -> 6.8166667 | E93: 2 | F93: 1 | L93: 6 | O93: 9 | U93: =COUNT(G93:S93) -> 2 | V93: 2 | W93: 2 | X93: 2 | Y93: 2 | Z93: 2 | AA93: 2 | AB93: 1 | AC93: 2 | AD93: 2 | AE93: 2 | AF93: 2 | AG93: 2 | AH93: 2 | AI93: 2 | AJ93: 2 | AK93: 2
A94: P61 | B94: 405 | C94: sec | D94: =B94/60 -> 6.75 | E94: 2 | F94: 2 | H94: 2 | J94: 4 | L94: 6 | N94: 8 | O94: 9 | Q94: 11 | R94: 12 | U94: =COUNT(G94:S94) -> 7 | V94: 4 | W94: 1 | X94: 1 | Y94: 1 | Z94: 4 | AA94: 5 | AB94: 2 | AC94: 5 | AD94: 3 | AE94: 3 | AF94: 4 | AG94: 3 | AH94: 4 | AI94: 4 | AJ94: 4 | AK94: 3
A95: P16 | B95: 401 | C95: sec | D95: =B95/60 -> 6.6833333 | E95: 1 | F95: 2 | H95: 2 | J95: 4 | L95: 6 | M95: 7 | O95: 9 | P95: 10 | R95: 12 | U95: =COUNT(G95:S95) -> 7 | V95: 4 | W95: 3 | X95: 3 | Y95: 3 | Z95: 4 | AA95: 4 | AB95: 2 | AC95: 4 | AD95: 4 | AE95: 4 | AF95: 4 | AG95: 4 | AH95: 5 | AI95: 4 | AJ95: 4 | AK95: 4
A96: P19 | B96: 401 | C96: sec | D96: =B96/60 -> 6.6833333 | E96: 2 | F96: 2 | T96: 14 | U96: =COUNT(G96:S96) -> 0 | V96: 6 | W96: 3 | X96: 3 | Y96: 3 | Z96: 3 | AA96: 3 | AB96: 7 | AC96: 3 | AD96: 3 | AE96: 3 | AF96: 3 | AG96: 3 | AH96: 3 | AI96: 3 | AJ96: 3 | AK96: 3
A97: P39 | B97: 401 | C97: sec | D97: =B97/60 -> 6.6833333 | E97: 2 | F97: 1 | H97: 2 | I97: 3 | J97: 4 | K97: 5 | L97: 6 | M97: 7 | N97: 8 | P97: 10 | R97: 12 | S97: 13 | U97: =COUNT(G97:S97) -> 10 | V97: 5 | W97: 4 | X97: 4 | Y97: 4 | Z97: 5 | AA97: 5 | AB97: 4 | AC97: 4 | AD97: 5 | AE97: 5 | AF97: 5 | AG97: 5 | AH97: 5 | AI97: 4 | AJ97: 4 | AK97: 4
A98: P60 | B98: 401 | C98: sec | D98: =B98/60 -> 6.6833333 | E98: 2 | F98: 3 | H98: 2 | J98: 4 | L98: 6 | U98: =COUNT(G98:S98) -> 3 | V98: 4 | W98: 4 | X98: 4 | Y98: 3 | Z98: 4 | AA98: 4 | AB98: 5 | AC98: 4 | AD98: 4 | AE98: 4 | AF98: 3 | AG98: 4 | AH98: 4 | AI98: 4 | AJ98: 4 | AK98: 3
A99: P13 | B99: 378 | C99: sec | D99: =B99/60 -> 6.3 | E99: 2 | F99: 6 | J99: 4 | K99: 5 | P99: 10 | R99: 12 | U99: =COUNT(G99:S99) -> 4 | V99: 5 | W99: 3 | X99: 3 | Y99: 3 | Z99: 4 | AA99: 5 | AB99: 1 | AC99: 4 | AD99: 4 | AE99: 5 | AF99: 4 | AG99: 5 | AH99: 5 | AI99: 4 | AJ99: 5 | AK99: 5
A100: P64 | B100: 378 | C100: sec | D100: =B100/60 -> 6.3 | E100: 2 | F100: 2 | H100: 2 | L100: 6 | Q100: 11 | U100: =COUNT(G100:S100) -> 3 | V100: 5 | W100: 5 | X100: 5 | Y100: 5 | Z100: 5 | AA100: 5 | AB100: 4 | AC100: 5 | AD100: 5 | AE100: 5 | AF100: 5 | AG100: 5 | AH100: 5 | AI100: 4 | AJ100: 3 | AK100: 4
...
